{
  "type": "FeatureCollection",
  "name": "平福乡",
  "properties": {
    "parentName": "藤县",
    "level": "town"
  },
  "features": [
    {
      "type": "Feature",
      "properties": {
        "OBJECTID": 8071,
        "region": "华南地区",
        "sheng": "广西壮族自治区",
        "shi": "梧州市",
        "xian": "藤县",
        "name": "平福乡",
        "lng": 110.78208772,
        "lat": 23.8174509191,
        "Shape_Leng": 111.410832879,
        "Shape_Area": 333.434720281
      },
      "geometry": {
        "type": "MultiPolygon",
        "coordinates": [
          [
            [
              [
                110.80961312574522,
                23.920420079223334
              ],
              [
                110.81022341827617,
                23.91873729299175
              ],
              [
                110.80935901960311,
                23.915867041930483
              ],
              [
                110.81676293835898,
                23.913050293336426
              ],
              [
                110.81665825817214,
                23.909023730860554
              ],
              [
                110.8179443777309,
                23.90804132494725
              ],
              [
                110.82142230159798,
                23.907277616169097
              ],
              [
                110.8222784417967,
                23.906028438961357
              ],
              [
                110.82515670401875,
                23.904956251030228
              ],
              [
                110.82468859700123,
                23.90365906621298
              ],
              [
                110.82578947960087,
                23.901965893711065
              ],
              [
                110.82723533584215,
                23.901285367725563
              ],
              [
                110.82983007599728,
                23.898258917914802
              ],
              [
                110.83375353569716,
                23.898754613434733
              ],
              [
                110.8346601746274,
                23.89680927103109
              ],
              [
                110.83762335803164,
                23.895783812772777
              ],
              [
                110.84113292274623,
                23.896160423664696
              ],
              [
                110.84176109559814,
                23.895545834172935
              ],
              [
                110.84600570499936,
                23.895902988232365
              ],
              [
                110.84751777742355,
                23.897266264226744
              ],
              [
                110.84908730933194,
                23.896349933302815
              ],
              [
                110.85111143684338,
                23.897461605069054
              ],
              [
                110.85466793897427,
                23.89543760705999
              ],
              [
                110.85270667677179,
                23.893418628167183
              ],
              [
                110.85362925078937,
                23.892148864578473
              ],
              [
                110.85432569387575,
                23.887590676868285
              ],
              [
                110.8552799024456,
                23.887339523200467
              ],
              [
                110.85542308170989,
                23.88491894215548
              ],
              [
                110.8565195603295,
                23.885212395435758
              ],
              [
                110.85935527112895,
                23.8840251338529
              ],
              [
                110.8601732485966,
                23.88217026864305
              ],
              [
                110.86274529076263,
                23.880992487713172
              ],
              [
                110.8636699341202,
                23.878017990837634
              ],
              [
                110.86308883538152,
                23.877795487771607
              ],
              [
                110.86334290824868,
                23.876292991328512
              ],
              [
                110.8676487641792,
                23.870194973619164
              ],
              [
                110.86860582539856,
                23.864919674603357
              ],
              [
                110.8670540308189,
                23.864978999281448
              ],
              [
                110.86474685878056,
                23.86345905059477
              ],
              [
                110.86224120276933,
                23.859880230887995
              ],
              [
                110.85912881464316,
                23.85719916211167
              ],
              [
                110.85871024857914,
                23.855823833403235
              ],
              [
                110.85754427844574,
                23.855391580557068
              ],
              [
                110.85731168588563,
                23.853566868716086
              ],
              [
                110.85604155537357,
                23.853548062992786
              ],
              [
                110.85537894927916,
                23.851902822557292
              ],
              [
                110.85273311863858,
                23.85042658991523
              ],
              [
                110.85101900272485,
                23.847171679929147
              ],
              [
                110.8504516096541,
                23.844097845739043
              ],
              [
                110.84927969680064,
                23.844015815877242
              ],
              [
                110.84526480392765,
                23.846248077087125
              ],
              [
                110.84191966585996,
                23.843244014100037
              ],
              [
                110.8327132386251,
                23.83983303486673
              ],
              [
                110.83156538713297,
                23.83692726867855
              ],
              [
                110.83186321471567,
                23.835996813002566
              ],
              [
                110.8387575740029,
                23.832618760647335
              ],
              [
                110.83961310086397,
                23.829250399386467
              ],
              [
                110.84700497589898,
                23.832258424786517
              ],
              [
                110.84618695976047,
                23.830925734734933
              ],
              [
                110.84692041264697,
                23.830140059116502
              ],
              [
                110.84634636279446,
                23.828839811208354
              ],
              [
                110.84704635280701,
                23.826802855767255
              ],
              [
                110.84429754709419,
                23.821055772405998
              ],
              [
                110.84565999481299,
                23.819099753251066
              ],
              [
                110.84639196831472,
                23.819710047580656
              ],
              [
                110.8471241279762,
                23.81709567432597
              ],
              [
                110.8503540323128,
                23.814098169195177
              ],
              [
                110.8493435441693,
                23.813086215156773
              ],
              [
                110.8492578513688,
                23.811481848008953
              ],
              [
                110.85035784274032,
                23.81069647366337
              ],
              [
                110.8506732529683,
                23.80926884937793
              ],
              [
                110.8519113891993,
                23.80954281974539
              ],
              [
                110.85272919309784,
                23.807986881089732
              ],
              [
                110.85517009162646,
                23.80850282844284
              ],
              [
                110.85642656503398,
                23.808054787098797
              ],
              [
                110.85945959158693,
                23.80937299896476
              ],
              [
                110.86143037401263,
                23.809086136815836
              ],
              [
                110.86357354927992,
                23.810788959043293
              ],
              [
                110.86599734540124,
                23.814497691215536
              ],
              [
                110.86756754370725,
                23.813728910261034
              ],
              [
                110.86974666127946,
                23.814950257948112
              ],
              [
                110.8727987633523,
                23.81485623562685
              ],
              [
                110.87726472109006,
                23.81787645583381
              ],
              [
                110.87951446781852,
                23.817750038133795
              ],
              [
                110.88162576661591,
                23.816644402617158
              ],
              [
                110.88547991376709,
                23.81671143268653
              ],
              [
                110.88771465800511,
                23.81408169991056
              ],
              [
                110.887281416804,
                23.811097072172174
              ],
              [
                110.88921942703502,
                23.80907232862512
              ],
              [
                110.88946501479865,
                23.8065737592716
              ],
              [
                110.8886294322026,
                23.804759831201295
              ],
              [
                110.88979879817606,
                23.803685614399626
              ],
              [
                110.88847516339814,
                23.801518720412673
              ],
              [
                110.88920920174331,
                23.799625627720616
              ],
              [
                110.88706747168652,
                23.79591773821312
              ],
              [
                110.88815060526628,
                23.79372040667147
              ],
              [
                110.89061036257823,
                23.792021180832876
              ],
              [
                110.89129246417593,
                23.789903850282542
              ],
              [
                110.89085822202941,
                23.788074194868273
              ],
              [
                110.88883548397047,
                23.788249320749628
              ],
              [
                110.88723135424368,
                23.787510065437232
              ],
              [
                110.88606523931941,
                23.78556773756111
              ],
              [
                110.88639950113611,
                23.78219834837512
              ],
              [
                110.8854597266851,
                23.780208033573956
              ],
              [
                110.88271035979534,
                23.777927441897987
              ],
              [
                110.8800144692924,
                23.777643802919215
              ],
              [
                110.87301442077893,
                23.774060197020503
              ],
              [
                110.87325985565786,
                23.771766809790506
              ],
              [
                110.87223435513147,
                23.768211527140295
              ],
              [
                110.8710322043728,
                23.766814822446122
              ],
              [
                110.87163514764399,
                23.765663709112914
              ],
              [
                110.87102253396284,
                23.76624284912822
              ],
              [
                110.86882795524599,
                23.76581114037191
              ],
              [
                110.8685310557637,
                23.768068406331963
              ],
              [
                110.86646428419942,
                23.77079300409389
              ],
              [
                110.86724949037176,
                23.77193966668233
              ],
              [
                110.86699727640325,
                23.772988640413473
              ],
              [
                110.86427027655208,
                23.773750079302772
              ],
              [
                110.86317640236916,
                23.77719334779482
              ],
              [
                110.85839719007834,
                23.77828950715508
              ],
              [
                110.856230800611,
                23.78147316835208
              ],
              [
                110.8512080258298,
                23.77913516125875
              ],
              [
                110.84895426182976,
                23.77967048000869
              ],
              [
                110.84401328398593,
                23.778922866397238
              ],
              [
                110.84412630628407,
                23.775733132977734
              ],
              [
                110.84536260070354,
                23.77402554164547
              ],
              [
                110.84661320333674,
                23.773715461699226
              ],
              [
                110.84848919092349,
                23.77105576711
              ],
              [
                110.84892277206836,
                23.769057542771407
              ],
              [
                110.85298355734534,
                23.76651237324745
              ],
              [
                110.85371804175429,
                23.765288234064826
              ],
              [
                110.85613078161032,
                23.765435864973256
              ],
              [
                110.8569379753074,
                23.76427091017439
              ],
              [
                110.85734172863795,
                23.762629181591535
              ],
              [
                110.8561248766618,
                23.757179759438372
              ],
              [
                110.85287121403536,
                23.753857081039484
              ],
              [
                110.85050148155818,
                23.75312701410047
              ],
              [
                110.84820895318069,
                23.750256308881603
              ],
              [
                110.84460970177639,
                23.75018245115922
              ],
              [
                110.842907136755,
                23.748950462693756
              ],
              [
                110.84098507779919,
                23.74934587481232
              ],
              [
                110.83936041744937,
                23.746669583234734
              ],
              [
                110.8370074950999,
                23.746496477230664
              ],
              [
                110.83529326227432,
                23.745500212764682
              ],
              [
                110.83535501602125,
                23.744218992712376
              ],
              [
                110.8332472452642,
                23.74209508092332
              ],
              [
                110.82883071426613,
                23.7408050034482
              ],
              [
                110.82690249585357,
                23.737515108935156
              ],
              [
                110.82456308491851,
                23.738854126616673
              ],
              [
                110.82006277217926,
                23.735920422089862
              ],
              [
                110.81860367611881,
                23.736034332018846
              ],
              [
                110.81842837127238,
                23.732583939996857
              ],
              [
                110.81750394914798,
                23.73089840723577
              ],
              [
                110.81505961970572,
                23.729119074285904
              ],
              [
                110.81156130101328,
                23.729504342951145
              ],
              [
                110.80974450860225,
                23.72829902208224
              ],
              [
                110.80887340188605,
                23.72883312225082
              ],
              [
                110.80819992029018,
                23.72780249379008
              ],
              [
                110.80634641485523,
                23.72766956140117
              ],
              [
                110.80613274672896,
                23.72667995461626
              ],
              [
                110.80505764319571,
                23.72777649528905
              ],
              [
                110.80412487806075,
                23.727699707575482
              ],
              [
                110.80183835715451,
                23.724637785805214
              ],
              [
                110.80222597125163,
                23.720854414399753
              ],
              [
                110.79968232517922,
                23.718957561642185
              ],
              [
                110.80039026070204,
                23.716262161269754
              ],
              [
                110.79815074825848,
                23.716706328334453
              ],
              [
                110.79763561119455,
                23.714614044802374
              ],
              [
                110.79962401673504,
                23.713270047574667
              ],
              [
                110.79994228410919,
                23.712160901104767
              ],
              [
                110.7992159961214,
                23.70899103191067
              ],
              [
                110.79846944011263,
                23.708457340034272
              ],
              [
                110.79676895432385,
                23.70954055904963
              ],
              [
                110.79498007686914,
                23.70874419139136
              ],
              [
                110.7925675843266,
                23.709796521392377
              ],
              [
                110.78862099316439,
                23.7093536043854
              ],
              [
                110.7797629282166,
                23.711438910976995
              ],
              [
                110.77774363635979,
                23.709627829260967
              ],
              [
                110.77611668004079,
                23.709499725332137
              ],
              [
                110.77472252582396,
                23.708340485724875
              ],
              [
                110.77194842128267,
                23.711083753412538
              ],
              [
                110.76711807443962,
                23.708815483347905
              ],
              [
                110.76486386707387,
                23.70993250518103
              ],
              [
                110.76373051714972,
                23.709207243319668
              ],
              [
                110.76235269911786,
                23.70978801020857
              ],
              [
                110.76002425991175,
                23.7088849433855
              ],
              [
                110.75838613041566,
                23.709791890783208
              ],
              [
                110.75587776025048,
                23.708717592143216
              ],
              [
                110.75193599035373,
                23.708892279155407
              ],
              [
                110.7496602658087,
                23.70824518276902
              ],
              [
                110.74701099166401,
                23.708944529766313
              ],
              [
                110.74775569237136,
                23.7132483262493
              ],
              [
                110.7462062908877,
                23.715789502783366
              ],
              [
                110.74351081856946,
                23.71505638174665
              ],
              [
                110.74319167705431,
                23.716171323447895
              ],
              [
                110.74229121286925,
                23.716235092575516
              ],
              [
                110.74046649563235,
                23.718203062821146
              ],
              [
                110.74021970727375,
                23.719355526936056
              ],
              [
                110.73838120702715,
                23.71887497060345
              ],
              [
                110.73615193876105,
                23.720136455033412
              ],
              [
                110.73482503314881,
                23.719636870844965
              ],
              [
                110.73481327631174,
                23.717547286178387
              ],
              [
                110.73232051477999,
                23.71686487791186
              ],
              [
                110.73001266735076,
                23.71842847789202
              ],
              [
                110.72819970425303,
                23.7185881300382
              ],
              [
                110.72697547244019,
                23.71401988700825
              ],
              [
                110.7274338793701,
                23.711399900185313
              ],
              [
                110.7266658853224,
                23.710699994709046
              ],
              [
                110.7224869480143,
                23.712014397946177
              ],
              [
                110.72053612244417,
                23.710583191661044
              ],
              [
                110.71803237299565,
                23.711232306126078
              ],
              [
                110.71637169839522,
                23.71229458892418
              ],
              [
                110.7192354932235,
                23.715395007073994
              ],
              [
                110.71927632694099,
                23.716842498282745
              ],
              [
                110.71867373530472,
                23.71768566666026
              ],
              [
                110.71768210684382,
                23.717048648076684
              ],
              [
                110.71613604993883,
                23.717608599257517
              ],
              [
                110.71292981036254,
                23.72183399824047
              ],
              [
                110.71464045579245,
                23.723238161911695
              ],
              [
                110.7138557748242,
                23.725021477958876
              ],
              [
                110.71269177870266,
                23.725713040424523
              ],
              [
                110.71205400019204,
                23.727967023859094
              ],
              [
                110.71295259108928,
                23.731278267378173
              ],
              [
                110.7114500973442,
                23.734575065986576
              ],
              [
                110.70815671975686,
                23.736682440142545
              ],
              [
                110.70464107292725,
                23.736761112835154
              ],
              [
                110.70347443729548,
                23.738055318198406
              ],
              [
                110.70467295299443,
                23.739182182212005
              ],
              [
                110.70391218140213,
                23.74010537316451
              ],
              [
                110.70112590633556,
                23.740531319964475
              ],
              [
                110.70002930091158,
                23.74335670474818
              ],
              [
                110.69615557641879,
                23.744005560208507
              ],
              [
                110.69512734555065,
                23.741195972016556
              ],
              [
                110.69094029006237,
                23.738391626872158
              ],
              [
                110.6877191801961,
                23.737996098741007
              ],
              [
                110.68642943726877,
                23.739161444744923
              ],
              [
                110.68445760263631,
                23.739303205778356
              ],
              [
                110.68440042374061,
                23.74151528170495
              ],
              [
                110.68210486374852,
                23.745627522592144
              ],
              [
                110.68315308564644,
                23.748089119017664
              ],
              [
                110.68613690399496,
                23.74938355370807
              ],
              [
                110.68725621010606,
                23.75296187159313
              ],
              [
                110.69062119441264,
                23.753830858607273
              ],
              [
                110.69294602823669,
                23.756097891204774
              ],
              [
                110.69334627870785,
                23.764715886628892
              ],
              [
                110.69278066629477,
                23.765861892712223
              ],
              [
                110.69410778684494,
                23.767050832430016
              ],
              [
                110.69415399581032,
                23.76825329435411
              ],
              [
                110.69134249116308,
                23.77251241521583
              ],
              [
                110.69263519375926,
                23.77329407356268
              ],
              [
                110.69269570913974,
                23.77543759057238
              ],
              [
                110.69490217059877,
                23.776853496691558
              ],
              [
                110.69393498571111,
                23.77938169960578
              ],
              [
                110.69464882168586,
                23.780061474657373
              ],
              [
                110.69808138914487,
                23.779992785338834
              ],
              [
                110.70087982574341,
                23.783205103432806
              ],
              [
                110.70418095998338,
                23.784617689255015
              ],
              [
                110.70438230919626,
                23.787575674577795
              ],
              [
                110.70875952633116,
                23.788661206649408
              ],
              [
                110.71471039516865,
                23.796133908253296
              ],
              [
                110.71211706784845,
                23.80058631770447
              ],
              [
                110.71418171881135,
                23.80551381740878
              ],
              [
                110.71055036970387,
                23.810178265414663
              ],
              [
                110.71274650784511,
                23.81246698606259
              ],
              [
                110.71315388724219,
                23.818399395415838
              ],
              [
                110.7111636749637,
                23.81943475431052
              ],
              [
                110.70966146900167,
                23.819271246770654
              ],
              [
                110.70882617328931,
                23.821739928055308
              ],
              [
                110.7095023996161,
                23.824554020052062
              ],
              [
                110.71264257859218,
                23.826455832570673
              ],
              [
                110.7140693656088,
                23.828351641215306
              ],
              [
                110.71419752169834,
                23.829628510347504
              ],
              [
                110.71299824607223,
                23.831074427742692
              ],
              [
                110.7136779392855,
                23.832360892641134
              ],
              [
                110.71315614993642,
                23.833746032053796
              ],
              [
                110.71560149381395,
                23.835296798708328
              ],
              [
                110.71516668959111,
                23.836791443170625
              ],
              [
                110.71693065942247,
                23.839569675600103
              ],
              [
                110.71489682193084,
                23.845358643086968
              ],
              [
                110.71523296422998,
                23.84648902434907
              ],
              [
                110.7131121056392,
                23.849170533793142
              ],
              [
                110.7121674280844,
                23.85382401096939
              ],
              [
                110.71351121756868,
                23.85655594180332
              ],
              [
                110.71950870456311,
                23.861375139750976
              ],
              [
                110.71874931432944,
                23.863829070355337
              ],
              [
                110.71989459915648,
                23.867472528834185
              ],
              [
                110.71883519508822,
                23.869619882351742
              ],
              [
                110.72082826811015,
                23.87036238511604
              ],
              [
                110.7238116511868,
                23.87537182025335
              ],
              [
                110.72222101938462,
                23.87831667907153
              ],
              [
                110.71971025342549,
                23.878900037806545
              ],
              [
                110.71842126413009,
                23.881650395749205
              ],
              [
                110.7190254871366,
                23.88342718271838
              ],
              [
                110.7211824544068,
                23.884386314177107
              ],
              [
                110.72018890499402,
                23.891065786756712
              ],
              [
                110.72085430438273,
                23.891929404818256
              ],
              [
                110.72329892700395,
                23.892283454417964
              ],
              [
                110.72591202591934,
                23.896676487929597
              ],
              [
                110.72986988378818,
                23.89736839843289
              ],
              [
                110.73103221976118,
                23.898903834344537
              ],
              [
                110.73287961879942,
                23.89876582438336
              ],
              [
                110.73697971344308,
                23.901390282635475
              ],
              [
                110.74009622586021,
                23.909698324917827
              ],
              [
                110.74265537264739,
                23.911960750288472
              ],
              [
                110.74291499613025,
                23.913687150941314
              ],
              [
                110.74144149293062,
                23.91493858994403
              ],
              [
                110.74083513673224,
                23.91703412002869
              ],
              [
                110.74253773772648,
                23.91943821470187
              ],
              [
                110.74215573629823,
                23.921183317656016
              ],
              [
                110.74400373608364,
                23.92270761906144
              ],
              [
                110.74514512594686,
                23.925968165998086
              ],
              [
                110.74717431034622,
                23.92717173139033
              ],
              [
                110.74808024690594,
                23.928690846405516
              ],
              [
                110.74720287011644,
                23.93067572300629
              ],
              [
                110.74821643124335,
                23.93200805782567
              ],
              [
                110.7503487633848,
                23.932017785792254
              ],
              [
                110.75085052393257,
                23.93321427172134
              ],
              [
                110.75330084555765,
                23.9338442962773
              ],
              [
                110.75661656230454,
                23.936307079807932
              ],
              [
                110.75731196127805,
                23.939124689952507
              ],
              [
                110.76260118809444,
                23.942475484755846
              ],
              [
                110.76276702577769,
                23.944452162237553
              ],
              [
                110.76637629742822,
                23.94786648784816
              ],
              [
                110.7675211640705,
                23.95016283474706
              ],
              [
                110.77566284076755,
                23.95152259529158
              ],
              [
                110.77869111800078,
                23.95011027387011
              ],
              [
                110.77913163111992,
                23.94918475187484
              ],
              [
                110.78011979359366,
                23.949345158552262
              ],
              [
                110.78319707218719,
                23.947580280405646
              ],
              [
                110.7841095387243,
                23.945909077442025
              ],
              [
                110.7832488353655,
                23.943724078303603
              ],
              [
                110.78527575527193,
                23.9429044712644
              ],
              [
                110.78515841982528,
                23.940796276027356
              ],
              [
                110.78778408586692,
                23.93914821981457
              ],
              [
                110.78878471114558,
                23.93629528519932
              ],
              [
                110.7943973620487,
                23.934906774228295
              ],
              [
                110.79528887618073,
                23.93205385220358
              ],
              [
                110.79726633337464,
                23.931240818309163
              ],
              [
                110.79791572303225,
                23.92947241392079
              ],
              [
                110.80394900574208,
                23.925499460032086
              ],
              [
                110.8050129163131,
                23.92378346723325
              ],
              [
                110.80759657861927,
                23.92224207601106
              ],
              [
                110.80787636580169,
                23.920925941579014
              ],
              [
                110.80895145134843,
                23.92098584002457
              ],
              [
                110.80961312574522,
                23.920420079223334
              ]
            ]
          ]
        ]
      }
    }
  ]
}
