{
  "type": "FeatureCollection",
  "name": "蒙江镇",
  "properties": {
    "parentName": "藤县",
    "level": "town"
  },
  "features": [
    {
      "type": "Feature",
      "properties": {
        "OBJECTID": 8073,
        "region": "华南地区",
        "sheng": "广西壮族自治区",
        "shi": "梧州市",
        "xian": "藤县",
        "name": "蒙江镇",
        "lng": 110.772598832,
        "lat": 23.5295269432,
        "Shape_Leng": 115.551670765,
        "Shape_Area": 299.182231851
      },
      "geometry": {
        "type": "MultiPolygon",
        "coordinates": [
          [
            [
              [
                110.80646613620331,
                23.63727848311555
              ],
              [
                110.80540188838648,
                23.63261961989957
              ],
              [
                110.8079632906734,
                23.63016738721518
              ],
              [
                110.80728780718664,
                23.625998971075717
              ],
              [
                110.80380509263097,
                23.62001041075189
              ],
              [
                110.80232390112718,
                23.61500626992347
              ],
              [
                110.80654118912463,
                23.606399407206936
              ],
              [
                110.80873274971668,
                23.60689965509505
              ],
              [
                110.81021927420022,
                23.60921911726848
              ],
              [
                110.81331615801435,
                23.61052940161062
              ],
              [
                110.8152254358053,
                23.610139632737912
              ],
              [
                110.81697016104414,
                23.61125446022521
              ],
              [
                110.81990526221813,
                23.610865567292137
              ],
              [
                110.82309401897385,
                23.612356214267948
              ],
              [
                110.8255646463914,
                23.611665201288076
              ],
              [
                110.82844919397519,
                23.61274288137895
              ],
              [
                110.82996909589713,
                23.614384943610332
              ],
              [
                110.82993402683394,
                23.616469217780207
              ],
              [
                110.8308981846036,
                23.61722913141932
              ],
              [
                110.83121704103365,
                23.619570212395445
              ],
              [
                110.8356336134006,
                23.619398902337537
              ],
              [
                110.8378604903694,
                23.618215511436745
              ],
              [
                110.84079638744339,
                23.619896025081516
              ],
              [
                110.84509121228967,
                23.618382600976304
              ],
              [
                110.84672710876913,
                23.618590319187945
              ],
              [
                110.84799938956024,
                23.61687003932093
              ],
              [
                110.85259117414341,
                23.617547621825338
              ],
              [
                110.85439839327131,
                23.616252734775912
              ],
              [
                110.85649687672952,
                23.61700628301361
              ],
              [
                110.86514885933246,
                23.614841899034445
              ],
              [
                110.86692727137654,
                23.614964195141567
              ],
              [
                110.8679639549726,
                23.613688496027294
              ],
              [
                110.86874231280757,
                23.609938270035173
              ],
              [
                110.87263943136475,
                23.608948541841755
              ],
              [
                110.87556659692098,
                23.60692062098991
              ],
              [
                110.87859856227391,
                23.60658148664635
              ],
              [
                110.88063808258153,
                23.604580416852798
              ],
              [
                110.88077155906024,
                23.605214997374276
              ],
              [
                110.87698520999948,
                23.598262604835384
              ],
              [
                110.87764184729349,
                23.58857899912158
              ],
              [
                110.87452885122559,
                23.58216821159374
              ],
              [
                110.87304037611256,
                23.582604204720326
              ],
              [
                110.86984507858756,
                23.581866088848983
              ],
              [
                110.86800349816298,
                23.58008354891672
              ],
              [
                110.86720686790267,
                23.577888965703266
              ],
              [
                110.86325913819871,
                23.57536632329726
              ],
              [
                110.86248188293263,
                23.573554100341482
              ],
              [
                110.86258249008989,
                23.57133540810264
              ],
              [
                110.86473033193931,
                23.570758391386676
              ],
              [
                110.86779546159136,
                23.565383476266447
              ],
              [
                110.87054779174724,
                23.564122243646693
              ],
              [
                110.873992042299,
                23.560851047837616
              ],
              [
                110.87588832668501,
                23.556411871011107
              ],
              [
                110.87476455274196,
                23.55513603969655
              ],
              [
                110.8721024587615,
                23.554814764090168
              ],
              [
                110.8665891541662,
                23.551933511622337
              ],
              [
                110.86470273624235,
                23.545404563969498
              ],
              [
                110.85902653025022,
                23.5410053251357
              ],
              [
                110.85553091941648,
                23.53857332000274
              ],
              [
                110.85256710378889,
                23.5385326886327
              ],
              [
                110.85200934695388,
                23.536945533609526
              ],
              [
                110.84953943899399,
                23.536791754036244
              ],
              [
                110.84838808734042,
                23.5357655547366
              ],
              [
                110.84806020801227,
                23.534588770255596
              ],
              [
                110.84914571220492,
                23.533705235808043
              ],
              [
                110.8485530697684,
                23.530638383954283
              ],
              [
                110.84957590740225,
                23.529627236607723
              ],
              [
                110.84939220468658,
                23.52814011407503
              ],
              [
                110.85043442720712,
                23.52743329011429
              ],
              [
                110.85022828460768,
                23.526277637003375
              ],
              [
                110.85179456276893,
                23.52480207795361
              ],
              [
                110.85604557444378,
                23.523807516803515
              ],
              [
                110.8554154860359,
                23.522363114765994
              ],
              [
                110.85688030268386,
                23.520765245219934
              ],
              [
                110.85467742322459,
                23.518663445961295
              ],
              [
                110.85418597520265,
                23.516742065993583
              ],
              [
                110.85493197812838,
                23.515039493777692
              ],
              [
                110.85263779589764,
                23.51317356780595
              ],
              [
                110.85147537808626,
                23.510888966053017
              ],
              [
                110.85179339814687,
                23.50920623108277
              ],
              [
                110.85062412930017,
                23.507317101702938
              ],
              [
                110.85171720398586,
                23.499500557804538
              ],
              [
                110.84775651325253,
                23.495765818138068
              ],
              [
                110.84768233267357,
                23.49410345281217
              ],
              [
                110.84583689775468,
                23.492778864752836
              ],
              [
                110.84587050362092,
                23.491633171633623
              ],
              [
                110.84444989494676,
                23.49033920099339
              ],
              [
                110.84578083132038,
                23.489521306263327
              ],
              [
                110.8451625995744,
                23.48691183161577
              ],
              [
                110.84198749272866,
                23.485070210721688
              ],
              [
                110.83675142034184,
                23.485828523567534
              ],
              [
                110.83588209338399,
                23.485306628098442
              ],
              [
                110.83605501322836,
                23.481819735292618
              ],
              [
                110.83531039615792,
                23.480278129132387
              ],
              [
                110.8357669657729,
                23.47674569285948
              ],
              [
                110.83456418009291,
                23.47527213210327
              ],
              [
                110.83368248116165,
                23.47048999341854
              ],
              [
                110.83515580899348,
                23.468567696142316
              ],
              [
                110.83403752900881,
                23.46532343772651
              ],
              [
                110.83306357402478,
                23.4645284658161
              ],
              [
                110.83389382094316,
                23.46250518816396
              ],
              [
                110.8336640378651,
                23.45917202906594
              ],
              [
                110.83711431207593,
                23.45830016332195
              ],
              [
                110.837369345419,
                23.454567465116497
              ],
              [
                110.83640049138961,
                23.454220890681597
              ],
              [
                110.8349726746493,
                23.450406972903522
              ],
              [
                110.83189497427372,
                23.44872224233768
              ],
              [
                110.83124835632663,
                23.447279361953065
              ],
              [
                110.82969196980861,
                23.446354010828998
              ],
              [
                110.82925854244786,
                23.44446198203491
              ],
              [
                110.82722305380094,
                23.44349062789024
              ],
              [
                110.82406407989345,
                23.443934708619963
              ],
              [
                110.8206025362781,
                23.441447161357473
              ],
              [
                110.81412275006494,
                23.44409391290378
              ],
              [
                110.80009289716952,
                23.456817894430344
              ],
              [
                110.79661413333565,
                23.458495726296803
              ],
              [
                110.7906009522722,
                23.458690796443136
              ],
              [
                110.78290099828251,
                23.46403600515754
              ],
              [
                110.77777712801213,
                23.466038735998893
              ],
              [
                110.76825477973438,
                23.46715079357432
              ],
              [
                110.76270462811618,
                23.467232718215428
              ],
              [
                110.74854298407149,
                23.465049585170277
              ],
              [
                110.73811847998394,
                23.461876551261867
              ],
              [
                110.73167724321024,
                23.45895268711689
              ],
              [
                110.7263912026919,
                23.45455370458984
              ],
              [
                110.7132539170347,
                23.446083267229028
              ],
              [
                110.70752734631003,
                23.44359242485058
              ],
              [
                110.70191946720968,
                23.442496081129264
              ],
              [
                110.68312463199624,
                23.441534406387802
              ],
              [
                110.67420488704596,
                23.44276252776848
              ],
              [
                110.6582500254184,
                23.44896773657183
              ],
              [
                110.6464413468907,
                23.455450357448115
              ],
              [
                110.63784859543637,
                23.456938150875033
              ],
              [
                110.63527940322194,
                23.456188281763843
              ],
              [
                110.62678011920718,
                23.45060416634925
              ],
              [
                110.61789625810587,
                23.448733188885626
              ],
              [
                110.6119075269109,
                23.44875834741987
              ],
              [
                110.61495769184404,
                23.451624777261713
              ],
              [
                110.61472369274429,
                23.45711164898347
              ],
              [
                110.61692114299643,
                23.45820271278501
              ],
              [
                110.61868764172135,
                23.457724501884286
              ],
              [
                110.62375542936962,
                23.46237422259236
              ],
              [
                110.62277306572446,
                23.466510703805966
              ],
              [
                110.62366455827282,
                23.468005187289634
              ],
              [
                110.62642133018028,
                23.46688629576596
              ],
              [
                110.6291137430049,
                23.467523004982752
              ],
              [
                110.6303775063169,
                23.47059223104668
              ],
              [
                110.63428775857324,
                23.472281601215002
              ],
              [
                110.63784419595294,
                23.475920640425272
              ],
              [
                110.64669722469722,
                23.47765597764129
              ],
              [
                110.6479135721537,
                23.47727746558263
              ],
              [
                110.64913826891603,
                23.4751524224464
              ],
              [
                110.65069278934084,
                23.47505065516367
              ],
              [
                110.65395496584904,
                23.47708499087969
              ],
              [
                110.65561290381254,
                23.476633643627792
              ],
              [
                110.65913951157927,
                23.477277165209046
              ],
              [
                110.6627214663227,
                23.480539003572233
              ],
              [
                110.6642299459553,
                23.483255016405906
              ],
              [
                110.66802598880838,
                23.482712547146377
              ],
              [
                110.67173419397795,
                23.48409779987361
              ],
              [
                110.67206438366446,
                23.485919775976924
              ],
              [
                110.67012635724564,
                23.487930178934675
              ],
              [
                110.66999404269097,
                23.490890196725275
              ],
              [
                110.66915994487562,
                23.492124336369102
              ],
              [
                110.67075278091619,
                23.49413481486988
              ],
              [
                110.67423208883991,
                23.493898381305314
              ],
              [
                110.67832803221296,
                23.49529683787881
              ],
              [
                110.68079529706534,
                23.4942245249419
              ],
              [
                110.68237311083044,
                23.49626469186211
              ],
              [
                110.68243260637973,
                23.49870179615101
              ],
              [
                110.68396067324653,
                23.49906644156306
              ],
              [
                110.68481870022288,
                23.50029881583771
              ],
              [
                110.68771973957439,
                23.50099018764712
              ],
              [
                110.69082772102257,
                23.50035793457107
              ],
              [
                110.69188620868164,
                23.501448234848226
              ],
              [
                110.6952723846129,
                23.50072350268755
              ],
              [
                110.69657827037094,
                23.50282083501355
              ],
              [
                110.69817848444956,
                23.502788676156513
              ],
              [
                110.69922016917553,
                23.50358414898932
              ],
              [
                110.69881790332363,
                23.504500080614264
              ],
              [
                110.70218646333467,
                23.505558765224862
              ],
              [
                110.70406244462617,
                23.510154570676946
              ],
              [
                110.7090818694328,
                23.517091839317004
              ],
              [
                110.71035048009065,
                23.52039876159364
              ],
              [
                110.71031293789184,
                23.522458004933014
              ],
              [
                110.71185284163539,
                23.52357843159939
              ],
              [
                110.71218296387275,
                23.524799496000014
              ],
              [
                110.71116586301423,
                23.5261775487549
              ],
              [
                110.71094840604417,
                23.52829884891281
              ],
              [
                110.71160282201271,
                23.52951057924986
              ],
              [
                110.71001358775692,
                23.530876137723624
              ],
              [
                110.70965189571848,
                23.53566889020715
              ],
              [
                110.71129372322679,
                23.53890780844864
              ],
              [
                110.7089533716009,
                23.54014613893321
              ],
              [
                110.70599371623706,
                23.539273681435304
              ],
              [
                110.70190707635055,
                23.541609456411322
              ],
              [
                110.70741395708853,
                23.5445993289959
              ],
              [
                110.71002782942082,
                23.54468445342485
              ],
              [
                110.71189781942888,
                23.547353305810475
              ],
              [
                110.70877397573844,
                23.548399599561947
              ],
              [
                110.70523717325699,
                23.547440602102142
              ],
              [
                110.70383871398553,
                23.546183977608507
              ],
              [
                110.7019179239731,
                23.547057177047122
              ],
              [
                110.70335934655668,
                23.549477211304293
              ],
              [
                110.7019956388877,
                23.55037455933848
              ],
              [
                110.70362143418191,
                23.551047861070003
              ],
              [
                110.70240541228003,
                23.55116604457737
              ],
              [
                110.70183103687293,
                23.551986471798273
              ],
              [
                110.69967449318335,
                23.551469592747537
              ],
              [
                110.69836833762872,
                23.552602162959488
              ],
              [
                110.69962654672781,
                23.55419416982511
              ],
              [
                110.70018401577977,
                23.55369515220957
              ],
              [
                110.69941444522055,
                23.55288616526434
              ],
              [
                110.69984032457137,
                23.552508062397237
              ],
              [
                110.7004486718688,
                23.55369612797398
              ],
              [
                110.70159504037889,
                23.553047482055717
              ],
              [
                110.7033873451499,
                23.555094268885455
              ],
              [
                110.70213942609371,
                23.55486069516502
              ],
              [
                110.70167388933857,
                23.555738760835197
              ],
              [
                110.7023135330432,
                23.556139574281985
              ],
              [
                110.70013070486817,
                23.556056930183217
              ],
              [
                110.70253231021798,
                23.554488168094508
              ],
              [
                110.70150742123059,
                23.553551938771022
              ],
              [
                110.69934612102674,
                23.55441733299358
              ],
              [
                110.69864039244021,
                23.555511726984662
              ],
              [
                110.69938721644695,
                23.557825804917
              ],
              [
                110.69828853898497,
                23.559235562371384
              ],
              [
                110.69974568711382,
                23.562026815185448
              ],
              [
                110.69945322308786,
                23.565037438726847
              ],
              [
                110.702550076325,
                23.569373654870333
              ],
              [
                110.70626726212453,
                23.571387747746428
              ],
              [
                110.71417358084614,
                23.57140184461946
              ],
              [
                110.71455377193911,
                23.570124193077106
              ],
              [
                110.71579496316707,
                23.571371041040777
              ],
              [
                110.71831539593882,
                23.5708529533012
              ],
              [
                110.7185632598866,
                23.571780228075113
              ],
              [
                110.72023624260856,
                23.57220781074193
              ],
              [
                110.71918574902315,
                23.575309654317152
              ],
              [
                110.71654338526906,
                23.57591552937822
              ],
              [
                110.71560423224958,
                23.57664670698
              ],
              [
                110.7158258207051,
                23.577686507626254
              ],
              [
                110.71634350644774,
                23.578877968143786
              ],
              [
                110.72161051821092,
                23.580058682662127
              ],
              [
                110.72230567077014,
                23.58306219256616
              ],
              [
                110.72358637461156,
                23.584814259870257
              ],
              [
                110.72578926036613,
                23.584969022402504
              ],
              [
                110.72682479013201,
                23.58398473870477
              ],
              [
                110.73047706376553,
                23.58294385257676
              ],
              [
                110.73391679162671,
                23.58415313585857
              ],
              [
                110.73702709782236,
                23.583527967641658
              ],
              [
                110.74173660456069,
                23.58777767529955
              ],
              [
                110.74154366221029,
                23.590284443772134
              ],
              [
                110.73981929132731,
                23.59211082115752
              ],
              [
                110.738476004564,
                23.59670359229699
              ],
              [
                110.7363060250031,
                23.598373895938607
              ],
              [
                110.7371209933392,
                23.599827819997927
              ],
              [
                110.73489789712033,
                23.60153437171391
              ],
              [
                110.73362650665803,
                23.605476028296096
              ],
              [
                110.73476959713923,
                23.60771407574407
              ],
              [
                110.73701415298086,
                23.60767486530284
              ],
              [
                110.73776258677401,
                23.609781628819178
              ],
              [
                110.73867296778332,
                23.609898730442126
              ],
              [
                110.73988959402959,
                23.607234042816856
              ],
              [
                110.74192453229142,
                23.607088710575567
              ],
              [
                110.74207979484669,
                23.60330167443277
              ],
              [
                110.74279122963162,
                23.60189272367029
              ],
              [
                110.74399021387734,
                23.601845109064584
              ],
              [
                110.74549195219191,
                23.598813902739494
              ],
              [
                110.74953050532861,
                23.600619560644247
              ],
              [
                110.74973296790222,
                23.601987691179033
              ],
              [
                110.75411208170726,
                23.60426010172239
              ],
              [
                110.75825052883891,
                23.60221133278685
              ],
              [
                110.75793829861362,
                23.59995652017733
              ],
              [
                110.76009506173779,
                23.5982762781278
              ],
              [
                110.76456468061559,
                23.598738458613013
              ],
              [
                110.7649363650213,
                23.601291507097415
              ],
              [
                110.76680916990733,
                23.602433415869484
              ],
              [
                110.7653795140534,
                23.605990028616986
              ],
              [
                110.76737446755772,
                23.606721609115027
              ],
              [
                110.76750828038291,
                23.608046734968866
              ],
              [
                110.77012376879696,
                23.611132575108286
              ],
              [
                110.76923986113076,
                23.612562795736494
              ],
              [
                110.76999694190539,
                23.613140906028036
              ],
              [
                110.76966984498739,
                23.61622892162751
              ],
              [
                110.76821251069885,
                23.61689008610864
              ],
              [
                110.76588763460671,
                23.62102432081582
              ],
              [
                110.76633408415074,
                23.624349699878792
              ],
              [
                110.76842170829525,
                23.6283681531678
              ],
              [
                110.77055827624349,
                23.629468825326057
              ],
              [
                110.77932407074934,
                23.62917518228886
              ],
              [
                110.78226645463326,
                23.629822578149515
              ],
              [
                110.78326347363048,
                23.629153336857087
              ],
              [
                110.78576911705119,
                23.632403189055992
              ],
              [
                110.78550902592087,
                23.633100963138986
              ],
              [
                110.78751202476019,
                23.634674106724674
              ],
              [
                110.79005463391428,
                23.634290920889327
              ],
              [
                110.791270032586,
                23.635463254625563
              ],
              [
                110.79350426331115,
                23.633385737961476
              ],
              [
                110.79504194303132,
                23.634517448421548
              ],
              [
                110.79940066560829,
                23.635000501272145
              ],
              [
                110.79988956315287,
                23.63603152183731
              ],
              [
                110.80189778975125,
                23.63624408919344
              ],
              [
                110.8056671281355,
                23.638213852687215
              ],
              [
                110.80646613620331,
                23.63727848311555
              ]
            ]
          ]
        ]
      }
    }
  ]
}
